postgres_cache/__init__.py
postgres_cache/base.py
postgres_cache/client_secondary_cache.py
postgres_cache/config.py
postgres_cache/migrations.py
postgres_cache/null_cache.py
postgres_cache/postgres_cache.py
postgres_cache/schema.py
postgres_cache/serialization.py
postgres_cache-0.1.1.dist-info/licenses/LICENSE
postgres_cache-0.1.1.dist-info/METADATA
postgres_cache-0.1.1.dist-info/WHEEL
postgres_cache-0.1.1.dist-info/top_level.txt
postgres_cache-0.1.1.dist-info/RECORD
