Metadata-Version: 2.4
Name: postgres-cache
Version: 0.1.1
Summary: PostgreSQL as a cache for Python applications
Author: Mykhailo Chalyi
Requires-Python: >=3.11
License-File: LICENSE
Requires-Dist: asyncpg>=0.29
Provides-Extra: dev
Requires-Dist: pytest>=7.4; extra == "dev"
Requires-Dist: pytest-asyncio>=0.23; extra == "dev"
Requires-Dist: anyio>=4.0; extra == "dev"
Requires-Dist: ruff>=0.8; extra == "dev"
Provides-Extra: examples
Requires-Dist: fastapi>=0.111; extra == "examples"
Requires-Dist: uvicorn>=0.30; extra == "examples"
Provides-Extra: benchmarks
Requires-Dist: redis>=5.0; extra == "benchmarks"
Dynamic: license-file
